indent_concluder/__init__.py
indent_concluder-1.1.3.dist-info/METADATA
indent_concluder-1.1.3.dist-info/WHEEL
indent_concluder-1.1.3.dist-info/entry_points.txt
indent_concluder-1.1.3.dist-info/top_level.txt
indent_concluder-1.1.3.dist-info/RECORD
