Metadata-Version: 2.1
Name: indent-concluder
Version: 1.1.3
Summary: UNKNOWN
Home-page: https://github.com/EvATive7/indent-concluder
Author: EvATive7
Author-email: 
License: UNKNOWN
Platform: UNKNOWN
Classifier: Programming Language :: Python :: 3
Classifier: License :: OSI Approved :: GNU Affero General Public License v3 or later (AGPLv3+)
Classifier: Operating System :: OS Independent
